sanic_cookiesession-0.3.1.dist-info/METADATA
sanic_cookiesession-0.3.1.dist-info/WHEEL
sanic_cookiesession-0.3.1.dist-info/licenses/AUTHORS
sanic_cookiesession-0.3.1.dist-info/licenses/LICENSE
sanic_cookiesession/__init__.py
sanic_cookiesession-0.3.1.dist-info/RECORD
