Metadata-Version: 2.1
Name: Sanic-CookieSession
Version: 0.3.1
Summary: Sanic-CookieSession - Simple Cookie-based Session for Sanic
Author-Email: Philip Xu <pyx@xrefactor.com>
License: BSD-New
Classifier: Development Status :: 4 - Beta
Classifier: Environment :: Web Environment
Classifier: Intended Audience :: Developers
Classifier: License :: OSI Approved :: BSD License
Classifier: Operating System :: OS Independent
Classifier: Programming Language :: Python :: 3
Classifier: Topic :: Internet :: WWW/HTTP :: Dynamic Content
Classifier: Topic :: Software Development :: Libraries :: Python Modules
Project-URL: Homepage, https://github.com/pyx/sanic-cookiesession/
Requires-Python: >=3.8
Requires-Dist: sanic>=21.3.0
Requires-Dist: itsdangerous
